Metadata-Version: 2.1
Name: dsm-django-masterdata
Version: 0.0.5
Summary: A simple way to use Master Data in django project.
Home-page: https://github.com/storemesh/masterdata/tree/django-app
Author: DigitalStoreMesh Co.,Ltd
Author-email: contact@storemesh.com
License: MIT License
Classifier: Intended Audience :: Developers
Classifier: License :: OSI Approved :: MIT License
Classifier: Operating System :: OS Independent
Classifier: Programming Language :: Python
Classifier: Programming Language :: Python :: 3.7
Classifier: Programming Language :: Python :: 3.8
